[
    {
        "index": "751",
        "date": "14/06/2012",
        "name": "Mark Denzel",
        "location": "Mt. Zion - Golden - US",
        "duration": "1:20",
        "distance": "9.2\u00a0km",
        "xckm": "14.0\u00a0km",
        "xcscore": "20.93",
        "wing": "Skywalk Poison3",
        "links": "http://xc.rmhpa.org/flight/217"
    },
    {
        "index": "752",
        "date": "30/06/2012",
        "name": "Ed Williams",
        "location": "Mt. Zion - Golden - US",
        "duration": "0:44",
        "distance": "11.4\u00a0km",
        "xckm": "13.9\u00a0km",
        "xcscore": "20.84",
        "wing": "Niviuk Peak 2",
        "links": "http://xc.rmhpa.org/flight/232"
    },
    {
        "index": "753",
        "date": "06/09/2017",
        "name": "Ryan Strong",
        "location": "Mt. Zion - Golden - US",
        "duration": "1:20",
        "distance": "3.1\u00a0km",
        "xckm": "11.8\u00a0km",
        "xcscore": "20.73",
        "wing": "Ozone rush 4",
        "links": "http://xc.rmhpa.org/flight/1599"
    },
    {
        "index": "754",
        "date": "29/07/2018",
        "name": "Ryan Strong",
        "location": "Mt. Zion - Golden - US",
        "duration": "0:55",
        "distance": "3.3\u00a0km",
        "xckm": "10.3\u00a0km",
        "xcscore": "20.69",
        "wing": "Ozone Alpina 3",
        "links": "http://xc.rmhpa.org/flight/1803"
    },
    {
        "index": "755",
        "date": "09/08/2015",
        "name": "Rick Damiani",
        "location": "Mt. Zion - Golden - US",
        "duration": "1:18",
        "distance": "10.4\u00a0km",
        "xckm": "13.7\u00a0km",
        "xcscore": "20.58",
        "wing": "Ozone delta 2",
        "links": "http://xc.rmhpa.org/flight/1133"
    },
    {
        "index": "756",
        "date": "18/06/2015",
        "name": "Ed Williams",
        "location": "Mt. Zion - Golden - US",
        "duration": "0:55",
        "distance": "10.5\u00a0km",
        "xckm": "13.7\u00a0km",
        "xcscore": "20.53",
        "wing": "Ozone Delta 2",
        "links": "http://xc.rmhpa.org/flight/1056"
    },
    {
        "index": "757",
        "date": "11/03/2018",
        "name": "Ryan Strong",
        "location": "Mt Herman - US",
        "duration": "1:39",
        "distance": "3.2\u00a0km",
        "xckm": "10.2\u00a0km",
        "xcscore": "20.44",
        "wing": "Ozone Alpina 3",
        "links": "http://xc.rmhpa.org/flight/1717"
    },
    {
        "index": "758",
        "date": "11/05/2013",
        "name": "Ed Williams",
        "location": "Mt. Zion - Golden - US",
        "duration": "1:29",
        "distance": "5.4\u00a0km",
        "xckm": "11.7\u00a0km",
        "xcscore": "20.43",
        "wing": "Skywalk Cayenne 3",
        "links": "http://xc.rmhpa.org/flight/507"
    },
    {
        "index": "759",
        "date": "01/02/2012",
        "name": "Kiernan O'Donovan",
        "location": "Mt. Zion - Golden - US",
        "duration": "0:45",
        "distance": "12.2\u00a0km",
        "xckm": "13.5\u00a0km",
        "xcscore": "20.31",
        "wing": "Ozone Delta",
        "links": "http://xc.rmhpa.org/flight/89"
    },
    {
        "index": "760",
        "date": "08/04/2016",
        "name": "Scott Sibs",
        "location": "Mt. Zion - Golden - US",
        "duration": "1:09",
        "distance": "4.9\u00a0km",
        "xckm": "11.6\u00a0km",
        "xcscore": "20.26",
        "wing": "Skywalk Chili 3S",
        "links": "http://xc.rmhpa.org/flight/1197"
    },
    {
        "index": "761",
        "date": "25/03/2018",
        "name": "William Stites",
        "location": "Boulder - US",
        "duration": "1:05",
        "distance": "2.7\u00a0km",
        "xckm": "13.5\u00a0km",
        "xcscore": "20.23",
        "wing": "UP Trango XRace",
        "links": "http://xc.rmhpa.org/flight/1755"
    },
    {
        "index": "762",
        "date": "15/04/2017",
        "name": "Rick Damiani",
        "location": "Mt. Zion - Golden - US",
        "duration": "0:46",
        "distance": "10.6\u00a0km",
        "xckm": "13.5\u00a0km",
        "xcscore": "20.22",
        "wing": "Gin Carrera+",
        "links": "http://xc.rmhpa.org/flight/1703"
    },
    {
        "index": "763",
        "date": "04/08/2013",
        "name": "Jason Ely",
        "location": "Mt. Zion - Golden - US",
        "duration": "1:18",
        "distance": "3.9\u00a0km",
        "xckm": "11.5\u00a0km",
        "xcscore": "20.16",
        "wing": "Ozone Delta",
        "links": "http://xc.rmhpa.org/flight/595"
    },
    {
        "index": "764",
        "date": "01/04/2012",
        "name": "Rick Damiani",
        "location": "Mt. Zion - Golden - US",
        "duration": "1:01",
        "distance": "10.4\u00a0km",
        "xckm": "13.4\u00a0km",
        "xcscore": "20.16",
        "wing": "Ozone M4",
        "links": "http://xc.rmhpa.org/flight/290"
    },
    {
        "index": "765",
        "date": "13/03/2018",
        "name": "Lex Shepherd",
        "location": "Boulder - US",
        "duration": "1:17",
        "distance": "6.2\u00a0km",
        "xckm": "13.4\u00a0km",
        "xcscore": "20.16",
        "wing": "Advance Sigma 10",
        "links": "http://xc.rmhpa.org/flight/1727"
    },
    {
        "index": "766",
        "date": "12/05/2016",
        "name": "Jacob Hildebrand",
        "location": "Mt. Zion - Golden - US",
        "duration": "0:46",
        "distance": "11.9\u00a0km",
        "xckm": "13.4\u00a0km",
        "xcscore": "20.16",
        "wing": "Advance Sigma 9",
        "links": "http://xc.rmhpa.org/flight/1215"
    },
    {
        "index": "767",
        "date": "12/05/2016",
        "name": "Ioannis Mellios",
        "location": "Mt. Zion - Golden - US",
        "duration": "0:48",
        "distance": "11.9\u00a0km",
        "xckm": "13.4\u00a0km",
        "xcscore": "20.10",
        "wing": "Gradient Aspen 2",
        "links": "http://xc.rmhpa.org/flight/1221"
    },
    {
        "index": "768",
        "date": "31/05/2012",
        "name": "Ed Williams",
        "location": "Mt. Zion - Golden - US",
        "duration": "2:22",
        "distance": "5.8\u00a0km",
        "xckm": "13.3\u00a0km",
        "xcscore": "19.90",
        "wing": "Niviuk Peak 2",
        "links": "http://xc.rmhpa.org/flight/212"
    },
    {
        "index": "769",
        "date": "03/08/2016",
        "name": "Ed Williams",
        "location": "Mt. Zion - Golden - US",
        "duration": "1:23",
        "distance": "6.3\u00a0km",
        "xckm": "13.3\u00a0km",
        "xcscore": "19.89",
        "wing": "Ozone Delta 2",
        "links": "http://xc.rmhpa.org/flight/1275"
    },
    {
        "index": "770",
        "date": "19/07/2017",
        "name": "Lex Shepherd",
        "location": "Boulder - US",
        "duration": "1:08",
        "distance": "10.5\u00a0km",
        "xckm": "13.2\u00a0km",
        "xcscore": "19.84",
        "wing": "Ozone Alpina2",
        "links": "http://xc.rmhpa.org/flight/1548"
    },
    {
        "index": "771",
        "date": "18/08/2013",
        "name": "Ed Williams",
        "location": "Mt. Zion - Golden - US",
        "duration": "0:48",
        "distance": "10.6\u00a0km",
        "xckm": "13.2\u00a0km",
        "xcscore": "19.75",
        "wing": "Ozone Delta 2",
        "links": "http://xc.rmhpa.org/flight/629"
    },
    {
        "index": "772",
        "date": "17/05/2014",
        "name": "Ed Williams",
        "location": "Mt. Zion - Golden - US",
        "duration": "0:55",
        "distance": "6.5\u00a0km",
        "xckm": "13.1\u00a0km",
        "xcscore": "19.60",
        "wing": "Ozone Delta 2",
        "links": "http://xc.rmhpa.org/flight/788"
    },
    {
        "index": "773",
        "date": "21/08/2014",
        "name": "Eric Bader",
        "location": "Mt. Zion - Golden - US",
        "duration": "0:51",
        "distance": "10.2\u00a0km",
        "xckm": "13.0\u00a0km",
        "xcscore": "19.55",
        "wing": "Ozone Ozone Buzz Z4",
        "links": "http://xc.rmhpa.org/flight/877"
    },
    {
        "index": "774",
        "date": "27/06/2015",
        "name": "Chris Ratay",
        "location": "Mt. Zion - Golden - US",
        "duration": "0:42",
        "distance": "11.5\u00a0km",
        "xckm": "13.0\u00a0km",
        "xcscore": "19.45",
        "wing": "Ozone Rush 4",
        "links": "http://xc.rmhpa.org/flight/1070"
    },
    {
        "index": "775",
        "date": "09/09/2012",
        "name": "Ed Williams",
        "location": "Upper Launch-Foothil... - US",
        "duration": "0:54",
        "distance": "10.0\u00a0km",
        "xckm": "12.9\u00a0km",
        "xcscore": "19.36",
        "wing": "Niviuk Peak 2",
        "links": "http://xc.rmhpa.org/flight/371"
    },
    {
        "index": "776",
        "date": "22/07/2017",
        "name": "Ryan Strong",
        "location": "Edna - US\u00a0[~0.5]",
        "duration": "1:43",
        "distance": "9.6\u00a0km",
        "xckm": "12.8\u00a0km",
        "xcscore": "19.23",
        "wing": "Ozone rush 4",
        "links": "http://xc.rmhpa.org/flight/1562"
    },
    {
        "index": "777",
        "date": "23/06/2014",
        "name": "Jan Voegeli",
        "location": "Mt. Zion - Golden - US",
        "duration": "1:00",
        "distance": "2.3\u00a0km",
        "xckm": "9.5\u00a0km",
        "xcscore": "19.01",
        "wing": "Ozone Mantra R12",
        "links": "http://xc.rmhpa.org/flight/820"
    },
    {
        "index": "778",
        "date": "26/06/2013",
        "name": "Amanda Brodbeck",
        "location": "Wolcott - US",
        "duration": "1:09",
        "distance": "4.3\u00a0km",
        "xckm": "12.6\u00a0km",
        "xcscore": "18.97",
        "wing": "Gradient Nevada",
        "links": "http://xc.rmhpa.org/flight/566"
    },
    {
        "index": "779",
        "date": "19/06/2012",
        "name": "Ed Williams",
        "location": "Mt. Zion - Golden - US",
        "duration": "1:30",
        "distance": "4.8\u00a0km",
        "xckm": "12.6\u00a0km",
        "xcscore": "18.86",
        "wing": "Niviuk Peak 2",
        "links": "http://xc.rmhpa.org/flight/233"
    },
    {
        "index": "780",
        "date": "12/09/2015",
        "name": "Rick Damiani",
        "location": "Mt. Zion - Golden - US",
        "duration": "1:15",
        "distance": "4.1\u00a0km",
        "xckm": "10.8\u00a0km",
        "xcscore": "18.82",
        "wing": "Ozone delta 2",
        "links": "http://xc.rmhpa.org/flight/1129"
    },
    {
        "index": "781",
        "date": "14/03/2015",
        "name": "Jacob Hildebrand",
        "location": "Upper Launch-Foothil... - US",
        "duration": "0:34",
        "distance": "10.0\u00a0km",
        "xckm": "12.5\u00a0km",
        "xcscore": "18.76",
        "wing": "Advance Sigma 9",
        "links": "http://xc.rmhpa.org/flight/940"
    },
    {
        "index": "782",
        "date": "21/10/2012",
        "name": "Jason Ely",
        "location": "Mt. Zion - Golden - US",
        "duration": "1:01",
        "distance": "3.4\u00a0km",
        "xckm": "10.7\u00a0km",
        "xcscore": "18.75",
        "wing": "Ozone Delta",
        "links": "http://xc.rmhpa.org/flight/432"
    },
    {
        "index": "783",
        "date": "11/03/2016",
        "name": "Mike Benzie",
        "location": "Mt. Zion - Golden - US",
        "duration": "1:28",
        "distance": "4.2\u00a0km",
        "xckm": "10.7\u00a0km",
        "xcscore": "18.69",
        "wing": "Gradient Nevada",
        "links": "http://xc.rmhpa.org/flight/1186"
    },
    {
        "index": "784",
        "date": "27/06/2015",
        "name": "Scott Sibs",
        "location": "Mt. Zion - Golden - US",
        "duration": "1:16",
        "distance": "4.5\u00a0km",
        "xckm": "10.6\u00a0km",
        "xcscore": "18.62",
        "wing": "Skywalk Mescal 4M",
        "links": "http://xc.rmhpa.org/flight/1063"
    },
    {
        "index": "785",
        "date": "16/08/2015",
        "name": "William Stites",
        "location": "Upper Launch-Foothil... - US\u00a0[~0.5]",
        "duration": "0:37",
        "distance": "4.6\u00a0km",
        "xckm": "10.6\u00a0km",
        "xcscore": "18.60",
        "wing": "Ozone Delta 2",
        "links": "http://xc.rmhpa.org/flight/1087"
    },
    {
        "index": "786",
        "date": "29/07/2018",
        "name": "Michael Jobin",
        "location": "Mt. Zion - Golden - US",
        "duration": "0:54",
        "distance": "11.0\u00a0km",
        "xckm": "12.4\u00a0km",
        "xcscore": "18.57",
        "wing": "Skywalk poison x alps",
        "links": "http://xc.rmhpa.org/flight/1802"
    },
    {
        "index": "787",
        "date": "21/07/2012",
        "name": "Michael Jobin",
        "location": "Mt. Zion - Golden - US",
        "duration": "1:13",
        "distance": "5.1\u00a0km",
        "xckm": "10.6\u00a0km",
        "xcscore": "18.54",
        "wing": "Aircross Usport Fr",
        "links": "http://xc.rmhpa.org/flight/271"
    },
    {
        "index": "788",
        "date": "15/06/2013",
        "name": "Rick Damiani",
        "location": "Mt. Zion - Golden - US",
        "duration": "1:25",
        "distance": "3.0\u00a0km",
        "xckm": "12.3\u00a0km",
        "xcscore": "18.38",
        "wing": "Gradient A4",
        "links": "http://xc.rmhpa.org/flight/556"
    },
    {
        "index": "789",
        "date": "26/04/2013",
        "name": "Gary Waterman",
        "location": "Mt. Zion - Golden - US",
        "duration": "0:56",
        "distance": "3.2\u00a0km",
        "xckm": "12.2\u00a0km",
        "xcscore": "18.38",
        "wing": "Aircross UCross",
        "links": "http://xc.rmhpa.org/flight/481"
    },
    {
        "index": "790",
        "date": "27/08/2017",
        "name": "Lex Shepherd",
        "location": "Boulder - US",
        "duration": "1:44",
        "distance": "3.8\u00a0km",
        "xckm": "10.5\u00a0km",
        "xcscore": "18.32",
        "wing": "Ozone Alpina2",
        "links": "http://xc.rmhpa.org/flight/1584"
    },
    {
        "index": "791",
        "date": "29/07/2012",
        "name": "Michael Jobin",
        "location": "Mt. Zion - Golden - US",
        "duration": "1:30",
        "distance": "5.4\u00a0km",
        "xckm": "12.2\u00a0km",
        "xcscore": "18.30",
        "wing": "Aircross usport Fr",
        "links": "http://xc.rmhpa.org/flight/293"
    },
    {
        "index": "792",
        "date": "09/06/2013",
        "name": "Amanda Brodbeck",
        "location": "Wolcott - US",
        "duration": "1:21",
        "distance": "3.7\u00a0km",
        "xckm": "9.1\u00a0km",
        "xcscore": "18.27",
        "wing": "Gradient Nevada",
        "links": "http://xc.rmhpa.org/flight/538"
    },
    {
        "index": "793",
        "date": "21/06/2013",
        "name": "Mike Benzie",
        "location": "Woodrat, Oregon - US",
        "duration": "1:34",
        "distance": "5.1\u00a0km",
        "xckm": "12.2\u00a0km",
        "xcscore": "18.24",
        "wing": "Gradient Nevada",
        "links": "http://xc.rmhpa.org/flight/709"
    },
    {
        "index": "794",
        "date": "01/07/2012",
        "name": "Gary Waterman",
        "location": "Villa Grove - US",
        "duration": "1:12",
        "distance": "7.1\u00a0km",
        "xckm": "12.1\u00a0km",
        "xcscore": "18.17",
        "wing": "Aircross UCross",
        "links": "http://xc.rmhpa.org/flight/251"
    },
    {
        "index": "795",
        "date": "23/04/2012",
        "name": "Jason Ely",
        "location": "Mt. Zion - Golden - US",
        "duration": "0:49",
        "distance": "4.1\u00a0km",
        "xckm": "10.3\u00a0km",
        "xcscore": "17.98",
        "wing": "Ozone Rush 3 ",
        "links": "http://xc.rmhpa.org/flight/154"
    },
    {
        "index": "796",
        "date": "01/06/2012",
        "name": "Mike Benzie",
        "location": "Mt. Zion - Golden - US",
        "duration": "1:09",
        "distance": "3.9\u00a0km",
        "xckm": "11.9\u00a0km",
        "xcscore": "17.91",
        "wing": "Gradient Golden 3",
        "links": "http://xc.rmhpa.org/flight/205"
    },
    {
        "index": "797",
        "date": "19/06/2016",
        "name": "Ed Williams",
        "location": "Mt. Zion - Golden - US",
        "duration": "1:11",
        "distance": "6.3\u00a0km",
        "xckm": "11.9\u00a0km",
        "xcscore": "17.90",
        "wing": "Ozone Delta 2",
        "links": "http://xc.rmhpa.org/flight/1245"
    },
    {
        "index": "798",
        "date": "14/05/2017",
        "name": "Shad Preston",
        "location": "Boulder - US",
        "duration": "0:26",
        "distance": "11.0\u00a0km",
        "xckm": "11.9\u00a0km",
        "xcscore": "17.79",
        "wing": "Ozone Mantra M6",
        "links": "http://xc.rmhpa.org/flight/1515"
    },
    {
        "index": "799",
        "date": "12/05/2016",
        "name": "Jacob Hildebrand",
        "location": "Mt. Zion - Golden - US",
        "duration": "0:47",
        "distance": "4.3\u00a0km",
        "xckm": "10.1\u00a0km",
        "xcscore": "17.75",
        "wing": "Advance Sigma 9",
        "links": "http://xc.rmhpa.org/flight/1216"
    },
    {
        "index": "800",
        "date": "19/06/2012",
        "name": "Jason Ely",
        "location": "Mt. Zion - Golden - US",
        "duration": "1:32",
        "distance": "4.6\u00a0km",
        "xckm": "10.1\u00a0km",
        "xcscore": "17.73",
        "wing": "Ozone Delta",
        "links": "http://xc.rmhpa.org/flight/226"
    },
    {
        "index": "751",
        "date": "14/06/2012",
        "name": "Mark Denzel",
        "location": "Mt. Zion - Golden - US",
        "duration": "1:20",
        "distance": "9.2\u00a0km",
        "xckm": "14.0\u00a0km",
        "xcscore": "20.93",
        "wing": "Skywalk Poison3",
        "links": "http://xc.rmhpa.org/flight/217"
    },
    {
        "index": "752",
        "date": "30/06/2012",
        "name": "Ed Williams",
        "location": "Mt. Zion - Golden - US",
        "duration": "0:44",
        "distance": "11.4\u00a0km",
        "xckm": "13.9\u00a0km",
        "xcscore": "20.84",
        "wing": "Niviuk Peak 2",
        "links": "http://xc.rmhpa.org/flight/232"
    },
    {
        "index": "753",
        "date": "06/09/2017",
        "name": "Ryan Strong",
        "location": "Mt. Zion - Golden - US",
        "duration": "1:20",
        "distance": "3.1\u00a0km",
        "xckm": "11.8\u00a0km",
        "xcscore": "20.73",
        "wing": "Ozone rush 4",
        "links": "http://xc.rmhpa.org/flight/1599"
    },
    {
        "index": "754",
        "date": "29/07/2018",
        "name": "Ryan Strong",
        "location": "Mt. Zion - Golden - US",
        "duration": "0:55",
        "distance": "3.3\u00a0km",
        "xckm": "10.3\u00a0km",
        "xcscore": "20.69",
        "wing": "Ozone Alpina 3",
        "links": "http://xc.rmhpa.org/flight/1803"
    },
    {
        "index": "755",
        "date": "09/08/2015",
        "name": "Rick Damiani",
        "location": "Mt. Zion - Golden - US",
        "duration": "1:18",
        "distance": "10.4\u00a0km",
        "xckm": "13.7\u00a0km",
        "xcscore": "20.58",
        "wing": "Ozone delta 2",
        "links": "http://xc.rmhpa.org/flight/1133"
    },
    {
        "index": "756",
        "date": "18/06/2015",
        "name": "Ed Williams",
        "location": "Mt. Zion - Golden - US",
        "duration": "0:55",
        "distance": "10.5\u00a0km",
        "xckm": "13.7\u00a0km",
        "xcscore": "20.53",
        "wing": "Ozone Delta 2",
        "links": "http://xc.rmhpa.org/flight/1056"
    },
    {
        "index": "757",
        "date": "11/03/2018",
        "name": "Ryan Strong",
        "location": "Mt Herman - US",
        "duration": "1:39",
        "distance": "3.2\u00a0km",
        "xckm": "10.2\u00a0km",
        "xcscore": "20.44",
        "wing": "Ozone Alpina 3",
        "links": "http://xc.rmhpa.org/flight/1717"
    },
    {
        "index": "758",
        "date": "11/05/2013",
        "name": "Ed Williams",
        "location": "Mt. Zion - Golden - US",
        "duration": "1:29",
        "distance": "5.4\u00a0km",
        "xckm": "11.7\u00a0km",
        "xcscore": "20.43",
        "wing": "Skywalk Cayenne 3",
        "links": "http://xc.rmhpa.org/flight/507"
    },
    {
        "index": "759",
        "date": "01/02/2012",
        "name": "Kiernan O'Donovan",
        "location": "Mt. Zion - Golden - US",
        "duration": "0:45",
        "distance": "12.2\u00a0km",
        "xckm": "13.5\u00a0km",
        "xcscore": "20.31",
        "wing": "Ozone Delta",
        "links": "http://xc.rmhpa.org/flight/89"
    },
    {
        "index": "760",
        "date": "08/04/2016",
        "name": "Scott Sibs",
        "location": "Mt. Zion - Golden - US",
        "duration": "1:09",
        "distance": "4.9\u00a0km",
        "xckm": "11.6\u00a0km",
        "xcscore": "20.26",
        "wing": "Skywalk Chili 3S",
        "links": "http://xc.rmhpa.org/flight/1197"
    },
    {
        "index": "761",
        "date": "25/03/2018",
        "name": "William Stites",
        "location": "Boulder - US",
        "duration": "1:05",
        "distance": "2.7\u00a0km",
        "xckm": "13.5\u00a0km",
        "xcscore": "20.23",
        "wing": "UP Trango XRace",
        "links": "http://xc.rmhpa.org/flight/1755"
    },
    {
        "index": "762",
        "date": "15/04/2017",
        "name": "Rick Damiani",
        "location": "Mt. Zion - Golden - US",
        "duration": "0:46",
        "distance": "10.6\u00a0km",
        "xckm": "13.5\u00a0km",
        "xcscore": "20.22",
        "wing": "Gin Carrera+",
        "links": "http://xc.rmhpa.org/flight/1703"
    },
    {
        "index": "763",
        "date": "04/08/2013",
        "name": "Jason Ely",
        "location": "Mt. Zion - Golden - US",
        "duration": "1:18",
        "distance": "3.9\u00a0km",
        "xckm": "11.5\u00a0km",
        "xcscore": "20.16",
        "wing": "Ozone Delta",
        "links": "http://xc.rmhpa.org/flight/595"
    },
    {
        "index": "764",
        "date": "01/04/2012",
        "name": "Rick Damiani",
        "location": "Mt. Zion - Golden - US",
        "duration": "1:01",
        "distance": "10.4\u00a0km",
        "xckm": "13.4\u00a0km",
        "xcscore": "20.16",
        "wing": "Ozone M4",
        "links": "http://xc.rmhpa.org/flight/290"
    },
    {
        "index": "765",
        "date": "13/03/2018",
        "name": "Lex Shepherd",
        "location": "Boulder - US",
        "duration": "1:17",
        "distance": "6.2\u00a0km",
        "xckm": "13.4\u00a0km",
        "xcscore": "20.16",
        "wing": "Advance Sigma 10",
        "links": "http://xc.rmhpa.org/flight/1727"
    },
    {
        "index": "766",
        "date": "12/05/2016",
        "name": "Jacob Hildebrand",
        "location": "Mt. Zion - Golden - US",
        "duration": "0:46",
        "distance": "11.9\u00a0km",
        "xckm": "13.4\u00a0km",
        "xcscore": "20.16",
        "wing": "Advance Sigma 9",
        "links": "http://xc.rmhpa.org/flight/1215"
    },
    {
        "index": "767",
        "date": "12/05/2016",
        "name": "Ioannis Mellios",
        "location": "Mt. Zion - Golden - US",
        "duration": "0:48",
        "distance": "11.9\u00a0km",
        "xckm": "13.4\u00a0km",
        "xcscore": "20.10",
        "wing": "Gradient Aspen 2",
        "links": "http://xc.rmhpa.org/flight/1221"
    },
    {
        "index": "768",
        "date": "31/05/2012",
        "name": "Ed Williams",
        "location": "Mt. Zion - Golden - US",
        "duration": "2:22",
        "distance": "5.8\u00a0km",
        "xckm": "13.3\u00a0km",
        "xcscore": "19.90",
        "wing": "Niviuk Peak 2",
        "links": "http://xc.rmhpa.org/flight/212"
    },
    {
        "index": "769",
        "date": "03/08/2016",
        "name": "Ed Williams",
        "location": "Mt. Zion - Golden - US",
        "duration": "1:23",
        "distance": "6.3\u00a0km",
        "xckm": "13.3\u00a0km",
        "xcscore": "19.89",
        "wing": "Ozone Delta 2",
        "links": "http://xc.rmhpa.org/flight/1275"
    },
    {
        "index": "770",
        "date": "19/07/2017",
        "name": "Lex Shepherd",
        "location": "Boulder - US",
        "duration": "1:08",
        "distance": "10.5\u00a0km",
        "xckm": "13.2\u00a0km",
        "xcscore": "19.84",
        "wing": "Ozone Alpina2",
        "links": "http://xc.rmhpa.org/flight/1548"
    },
    {
        "index": "771",
        "date": "18/08/2013",
        "name": "Ed Williams",
        "location": "Mt. Zion - Golden - US",
        "duration": "0:48",
        "distance": "10.6\u00a0km",
        "xckm": "13.2\u00a0km",
        "xcscore": "19.75",
        "wing": "Ozone Delta 2",
        "links": "http://xc.rmhpa.org/flight/629"
    },
    {
        "index": "772",
        "date": "17/05/2014",
        "name": "Ed Williams",
        "location": "Mt. Zion - Golden - US",
        "duration": "0:55",
        "distance": "6.5\u00a0km",
        "xckm": "13.1\u00a0km",
        "xcscore": "19.60",
        "wing": "Ozone Delta 2",
        "links": "http://xc.rmhpa.org/flight/788"
    },
    {
        "index": "773",
        "date": "21/08/2014",
        "name": "Eric Bader",
        "location": "Mt. Zion - Golden - US",
        "duration": "0:51",
        "distance": "10.2\u00a0km",
        "xckm": "13.0\u00a0km",
        "xcscore": "19.55",
        "wing": "Ozone Ozone Buzz Z4",
        "links": "http://xc.rmhpa.org/flight/877"
    },
    {
        "index": "774",
        "date": "27/06/2015",
        "name": "Chris Ratay",
        "location": "Mt. Zion - Golden - US",
        "duration": "0:42",
        "distance": "11.5\u00a0km",
        "xckm": "13.0\u00a0km",
        "xcscore": "19.45",
        "wing": "Ozone Rush 4",
        "links": "http://xc.rmhpa.org/flight/1070"
    },
    {
        "index": "775",
        "date": "09/09/2012",
        "name": "Ed Williams",
        "location": "Upper Launch-Foothil... - US",
        "duration": "0:54",
        "distance": "10.0\u00a0km",
        "xckm": "12.9\u00a0km",
        "xcscore": "19.36",
        "wing": "Niviuk Peak 2",
        "links": "http://xc.rmhpa.org/flight/371"
    },
    {
        "index": "776",
        "date": "22/07/2017",
        "name": "Ryan Strong",
        "location": "Edna - US\u00a0[~0.5]",
        "duration": "1:43",
        "distance": "9.6\u00a0km",
        "xckm": "12.8\u00a0km",
        "xcscore": "19.23",
        "wing": "Ozone rush 4",
        "links": "http://xc.rmhpa.org/flight/1562"
    },
    {
        "index": "777",
        "date": "23/06/2014",
        "name": "Jan Voegeli",
        "location": "Mt. Zion - Golden - US",
        "duration": "1:00",
        "distance": "2.3\u00a0km",
        "xckm": "9.5\u00a0km",
        "xcscore": "19.01",
        "wing": "Ozone Mantra R12",
        "links": "http://xc.rmhpa.org/flight/820"
    },
    {
        "index": "778",
        "date": "26/06/2013",
        "name": "Amanda Brodbeck",
        "location": "Wolcott - US",
        "duration": "1:09",
        "distance": "4.3\u00a0km",
        "xckm": "12.6\u00a0km",
        "xcscore": "18.97",
        "wing": "Gradient Nevada",
        "links": "http://xc.rmhpa.org/flight/566"
    },
    {
        "index": "779",
        "date": "19/06/2012",
        "name": "Ed Williams",
        "location": "Mt. Zion - Golden - US",
        "duration": "1:30",
        "distance": "4.8\u00a0km",
        "xckm": "12.6\u00a0km",
        "xcscore": "18.86",
        "wing": "Niviuk Peak 2",
        "links": "http://xc.rmhpa.org/flight/233"
    },
    {
        "index": "780",
        "date": "12/09/2015",
        "name": "Rick Damiani",
        "location": "Mt. Zion - Golden - US",
        "duration": "1:15",
        "distance": "4.1\u00a0km",
        "xckm": "10.8\u00a0km",
        "xcscore": "18.82",
        "wing": "Ozone delta 2",
        "links": "http://xc.rmhpa.org/flight/1129"
    },
    {
        "index": "781",
        "date": "14/03/2015",
        "name": "Jacob Hildebrand",
        "location": "Upper Launch-Foothil... - US",
        "duration": "0:34",
        "distance": "10.0\u00a0km",
        "xckm": "12.5\u00a0km",
        "xcscore": "18.76",
        "wing": "Advance Sigma 9",
        "links": "http://xc.rmhpa.org/flight/940"
    },
    {
        "index": "782",
        "date": "21/10/2012",
        "name": "Jason Ely",
        "location": "Mt. Zion - Golden - US",
        "duration": "1:01",
        "distance": "3.4\u00a0km",
        "xckm": "10.7\u00a0km",
        "xcscore": "18.75",
        "wing": "Ozone Delta",
        "links": "http://xc.rmhpa.org/flight/432"
    },
    {
        "index": "783",
        "date": "11/03/2016",
        "name": "Mike Benzie",
        "location": "Mt. Zion - Golden - US",
        "duration": "1:28",
        "distance": "4.2\u00a0km",
        "xckm": "10.7\u00a0km",
        "xcscore": "18.69",
        "wing": "Gradient Nevada",
        "links": "http://xc.rmhpa.org/flight/1186"
    },
    {
        "index": "784",
        "date": "27/06/2015",
        "name": "Scott Sibs",
        "location": "Mt. Zion - Golden - US",
        "duration": "1:16",
        "distance": "4.5\u00a0km",
        "xckm": "10.6\u00a0km",
        "xcscore": "18.62",
        "wing": "Skywalk Mescal 4M",
        "links": "http://xc.rmhpa.org/flight/1063"
    },
    {
        "index": "785",
        "date": "16/08/2015",
        "name": "William Stites",
        "location": "Upper Launch-Foothil... - US\u00a0[~0.5]",
        "duration": "0:37",
        "distance": "4.6\u00a0km",
        "xckm": "10.6\u00a0km",
        "xcscore": "18.60",
        "wing": "Ozone Delta 2",
        "links": "http://xc.rmhpa.org/flight/1087"
    },
    {
        "index": "786",
        "date": "29/07/2018",
        "name": "Michael Jobin",
        "location": "Mt. Zion - Golden - US",
        "duration": "0:54",
        "distance": "11.0\u00a0km",
        "xckm": "12.4\u00a0km",
        "xcscore": "18.57",
        "wing": "Skywalk poison x alps",
        "links": "http://xc.rmhpa.org/flight/1802"
    },
    {
        "index": "787",
        "date": "21/07/2012",
        "name": "Michael Jobin",
        "location": "Mt. Zion - Golden - US",
        "duration": "1:13",
        "distance": "5.1\u00a0km",
        "xckm": "10.6\u00a0km",
        "xcscore": "18.54",
        "wing": "Aircross Usport Fr",
        "links": "http://xc.rmhpa.org/flight/271"
    },
    {
        "index": "788",
        "date": "15/06/2013",
        "name": "Rick Damiani",
        "location": "Mt. Zion - Golden - US",
        "duration": "1:25",
        "distance": "3.0\u00a0km",
        "xckm": "12.3\u00a0km",
        "xcscore": "18.38",
        "wing": "Gradient A4",
        "links": "http://xc.rmhpa.org/flight/556"
    },
    {
        "index": "789",
        "date": "26/04/2013",
        "name": "Gary Waterman",
        "location": "Mt. Zion - Golden - US",
        "duration": "0:56",
        "distance": "3.2\u00a0km",
        "xckm": "12.2\u00a0km",
        "xcscore": "18.38",
        "wing": "Aircross UCross",
        "links": "http://xc.rmhpa.org/flight/481"
    },
    {
        "index": "790",
        "date": "27/08/2017",
        "name": "Lex Shepherd",
        "location": "Boulder - US",
        "duration": "1:44",
        "distance": "3.8\u00a0km",
        "xckm": "10.5\u00a0km",
        "xcscore": "18.32",
        "wing": "Ozone Alpina2",
        "links": "http://xc.rmhpa.org/flight/1584"
    },
    {
        "index": "791",
        "date": "29/07/2012",
        "name": "Michael Jobin",
        "location": "Mt. Zion - Golden - US",
        "duration": "1:30",
        "distance": "5.4\u00a0km",
        "xckm": "12.2\u00a0km",
        "xcscore": "18.30",
        "wing": "Aircross usport Fr",
        "links": "http://xc.rmhpa.org/flight/293"
    },
    {
        "index": "792",
        "date": "09/06/2013",
        "name": "Amanda Brodbeck",
        "location": "Wolcott - US",
        "duration": "1:21",
        "distance": "3.7\u00a0km",
        "xckm": "9.1\u00a0km",
        "xcscore": "18.27",
        "wing": "Gradient Nevada",
        "links": "http://xc.rmhpa.org/flight/538"
    },
    {
        "index": "793",
        "date": "21/06/2013",
        "name": "Mike Benzie",
        "location": "Woodrat, Oregon - US",
        "duration": "1:34",
        "distance": "5.1\u00a0km",
        "xckm": "12.2\u00a0km",
        "xcscore": "18.24",
        "wing": "Gradient Nevada",
        "links": "http://xc.rmhpa.org/flight/709"
    },
    {
        "index": "794",
        "date": "01/07/2012",
        "name": "Gary Waterman",
        "location": "Villa Grove - US",
        "duration": "1:12",
        "distance": "7.1\u00a0km",
        "xckm": "12.1\u00a0km",
        "xcscore": "18.17",
        "wing": "Aircross UCross",
        "links": "http://xc.rmhpa.org/flight/251"
    },
    {
        "index": "795",
        "date": "23/04/2012",
        "name": "Jason Ely",
        "location": "Mt. Zion - Golden - US",
        "duration": "0:49",
        "distance": "4.1\u00a0km",
        "xckm": "10.3\u00a0km",
        "xcscore": "17.98",
        "wing": "Ozone Rush 3 ",
        "links": "http://xc.rmhpa.org/flight/154"
    },
    {
        "index": "796",
        "date": "01/06/2012",
        "name": "Mike Benzie",
        "location": "Mt. Zion - Golden - US",
        "duration": "1:09",
        "distance": "3.9\u00a0km",
        "xckm": "11.9\u00a0km",
        "xcscore": "17.91",
        "wing": "Gradient Golden 3",
        "links": "http://xc.rmhpa.org/flight/205"
    },
    {
        "index": "797",
        "date": "19/06/2016",
        "name": "Ed Williams",
        "location": "Mt. Zion - Golden - US",
        "duration": "1:11",
        "distance": "6.3\u00a0km",
        "xckm": "11.9\u00a0km",
        "xcscore": "17.90",
        "wing": "Ozone Delta 2",
        "links": "http://xc.rmhpa.org/flight/1245"
    },
    {
        "index": "798",
        "date": "14/05/2017",
        "name": "Shad Preston",
        "location": "Boulder - US",
        "duration": "0:26",
        "distance": "11.0\u00a0km",
        "xckm": "11.9\u00a0km",
        "xcscore": "17.79",
        "wing": "Ozone Mantra M6",
        "links": "http://xc.rmhpa.org/flight/1515"
    },
    {
        "index": "799",
        "date": "12/05/2016",
        "name": "Jacob Hildebrand",
        "location": "Mt. Zion - Golden - US",
        "duration": "0:47",
        "distance": "4.3\u00a0km",
        "xckm": "10.1\u00a0km",
        "xcscore": "17.75",
        "wing": "Advance Sigma 9",
        "links": "http://xc.rmhpa.org/flight/1216"
    },
    {
        "index": "800",
        "date": "19/06/2012",
        "name": "Jason Ely",
        "location": "Mt. Zion - Golden - US",
        "duration": "1:32",
        "distance": "4.6\u00a0km",
        "xckm": "10.1\u00a0km",
        "xcscore": "17.73",
        "wing": "Ozone Delta",
        "links": "http://xc.rmhpa.org/flight/226"
    },
    {
        "index": "751",
        "date": "14/06/2012",
        "name": "Mark Denzel",
        "location": "Mt. Zion - Golden - US",
        "duration": "1:20",
        "distance": "9.2\u00a0km",
        "xckm": "14.0\u00a0km",
        "xcscore": "20.93",
        "wing": "Skywalk Poison3",
        "links": "http://xc.rmhpa.org/flight/217"
    },
    {
        "index": "752",
        "date": "30/06/2012",
        "name": "Ed Williams",
        "location": "Mt. Zion - Golden - US",
        "duration": "0:44",
        "distance": "11.4\u00a0km",
        "xckm": "13.9\u00a0km",
        "xcscore": "20.84",
        "wing": "Niviuk Peak 2",
        "links": "http://xc.rmhpa.org/flight/232"
    },
    {
        "index": "753",
        "date": "06/09/2017",
        "name": "Ryan Strong",
        "location": "Mt. Zion - Golden - US",
        "duration": "1:20",
        "distance": "3.1\u00a0km",
        "xckm": "11.8\u00a0km",
        "xcscore": "20.73",
        "wing": "Ozone rush 4",
        "links": "http://xc.rmhpa.org/flight/1599"
    },
    {
        "index": "754",
        "date": "29/07/2018",
        "name": "Ryan Strong",
        "location": "Mt. Zion - Golden - US",
        "duration": "0:55",
        "distance": "3.3\u00a0km",
        "xckm": "10.3\u00a0km",
        "xcscore": "20.69",
        "wing": "Ozone Alpina 3",
        "links": "http://xc.rmhpa.org/flight/1803"
    },
    {
        "index": "755",
        "date": "09/08/2015",
        "name": "Rick Damiani",
        "location": "Mt. Zion - Golden - US",
        "duration": "1:18",
        "distance": "10.4\u00a0km",
        "xckm": "13.7\u00a0km",
        "xcscore": "20.58",
        "wing": "Ozone delta 2",
        "links": "http://xc.rmhpa.org/flight/1133"
    },
    {
        "index": "756",
        "date": "18/06/2015",
        "name": "Ed Williams",
        "location": "Mt. Zion - Golden - US",
        "duration": "0:55",
        "distance": "10.5\u00a0km",
        "xckm": "13.7\u00a0km",
        "xcscore": "20.53",
        "wing": "Ozone Delta 2",
        "links": "http://xc.rmhpa.org/flight/1056"
    },
    {
        "index": "757",
        "date": "11/03/2018",
        "name": "Ryan Strong",
        "location": "Mt Herman - US",
        "duration": "1:39",
        "distance": "3.2\u00a0km",
        "xckm": "10.2\u00a0km",
        "xcscore": "20.44",
        "wing": "Ozone Alpina 3",
        "links": "http://xc.rmhpa.org/flight/1717"
    },
    {
        "index": "758",
        "date": "11/05/2013",
        "name": "Ed Williams",
        "location": "Mt. Zion - Golden - US",
        "duration": "1:29",
        "distance": "5.4\u00a0km",
        "xckm": "11.7\u00a0km",
        "xcscore": "20.43",
        "wing": "Skywalk Cayenne 3",
        "links": "http://xc.rmhpa.org/flight/507"
    },
    {
        "index": "759",
        "date": "01/02/2012",
        "name": "Kiernan O'Donovan",
        "location": "Mt. Zion - Golden - US",
        "duration": "0:45",
        "distance": "12.2\u00a0km",
        "xckm": "13.5\u00a0km",
        "xcscore": "20.31",
        "wing": "Ozone Delta",
        "links": "http://xc.rmhpa.org/flight/89"
    },
    {
        "index": "760",
        "date": "08/04/2016",
        "name": "Scott Sibs",
        "location": "Mt. Zion - Golden - US",
        "duration": "1:09",
        "distance": "4.9\u00a0km",
        "xckm": "11.6\u00a0km",
        "xcscore": "20.26",
        "wing": "Skywalk Chili 3S",
        "links": "http://xc.rmhpa.org/flight/1197"
    },
    {
        "index": "761",
        "date": "25/03/2018",
        "name": "William Stites",
        "location": "Boulder - US",
        "duration": "1:05",
        "distance": "2.7\u00a0km",
        "xckm": "13.5\u00a0km",
        "xcscore": "20.23",
        "wing": "UP Trango XRace",
        "links": "http://xc.rmhpa.org/flight/1755"
    },
    {
        "index": "762",
        "date": "15/04/2017",
        "name": "Rick Damiani",
        "location": "Mt. Zion - Golden - US",
        "duration": "0:46",
        "distance": "10.6\u00a0km",
        "xckm": "13.5\u00a0km",
        "xcscore": "20.22",
        "wing": "Gin Carrera+",
        "links": "http://xc.rmhpa.org/flight/1703"
    },
    {
        "index": "763",
        "date": "04/08/2013",
        "name": "Jason Ely",
        "location": "Mt. Zion - Golden - US",
        "duration": "1:18",
        "distance": "3.9\u00a0km",
        "xckm": "11.5\u00a0km",
        "xcscore": "20.16",
        "wing": "Ozone Delta",
        "links": "http://xc.rmhpa.org/flight/595"
    },
    {
        "index": "764",
        "date": "01/04/2012",
        "name": "Rick Damiani",
        "location": "Mt. Zion - Golden - US",
        "duration": "1:01",
        "distance": "10.4\u00a0km",
        "xckm": "13.4\u00a0km",
        "xcscore": "20.16",
        "wing": "Ozone M4",
        "links": "http://xc.rmhpa.org/flight/290"
    },
    {
        "index": "765",
        "date": "13/03/2018",
        "name": "Lex Shepherd",
        "location": "Boulder - US",
        "duration": "1:17",
        "distance": "6.2\u00a0km",
        "xckm": "13.4\u00a0km",
        "xcscore": "20.16",
        "wing": "Advance Sigma 10",
        "links": "http://xc.rmhpa.org/flight/1727"
    },
    {
        "index": "766",
        "date": "12/05/2016",
        "name": "Jacob Hildebrand",
        "location": "Mt. Zion - Golden - US",
        "duration": "0:46",
        "distance": "11.9\u00a0km",
        "xckm": "13.4\u00a0km",
        "xcscore": "20.16",
        "wing": "Advance Sigma 9",
        "links": "http://xc.rmhpa.org/flight/1215"
    },
    {
        "index": "767",
        "date": "12/05/2016",
        "name": "Ioannis Mellios",
        "location": "Mt. Zion - Golden - US",
        "duration": "0:48",
        "distance": "11.9\u00a0km",
        "xckm": "13.4\u00a0km",
        "xcscore": "20.10",
        "wing": "Gradient Aspen 2",
        "links": "http://xc.rmhpa.org/flight/1221"
    },
    {
        "index": "768",
        "date": "31/05/2012",
        "name": "Ed Williams",
        "location": "Mt. Zion - Golden - US",
        "duration": "2:22",
        "distance": "5.8\u00a0km",
        "xckm": "13.3\u00a0km",
        "xcscore": "19.90",
        "wing": "Niviuk Peak 2",
        "links": "http://xc.rmhpa.org/flight/212"
    },
    {
        "index": "769",
        "date": "03/08/2016",
        "name": "Ed Williams",
        "location": "Mt. Zion - Golden - US",
        "duration": "1:23",
        "distance": "6.3\u00a0km",
        "xckm": "13.3\u00a0km",
        "xcscore": "19.89",
        "wing": "Ozone Delta 2",
        "links": "http://xc.rmhpa.org/flight/1275"
    },
    {
        "index": "770",
        "date": "19/07/2017",
        "name": "Lex Shepherd",
        "location": "Boulder - US",
        "duration": "1:08",
        "distance": "10.5\u00a0km",
        "xckm": "13.2\u00a0km",
        "xcscore": "19.84",
        "wing": "Ozone Alpina2",
        "links": "http://xc.rmhpa.org/flight/1548"
    },
    {
        "index": "771",
        "date": "18/08/2013",
        "name": "Ed Williams",
        "location": "Mt. Zion - Golden - US",
        "duration": "0:48",
        "distance": "10.6\u00a0km",
        "xckm": "13.2\u00a0km",
        "xcscore": "19.75",
        "wing": "Ozone Delta 2",
        "links": "http://xc.rmhpa.org/flight/629"
    },
    {
        "index": "772",
        "date": "17/05/2014",
        "name": "Ed Williams",
        "location": "Mt. Zion - Golden - US",
        "duration": "0:55",
        "distance": "6.5\u00a0km",
        "xckm": "13.1\u00a0km",
        "xcscore": "19.60",
        "wing": "Ozone Delta 2",
        "links": "http://xc.rmhpa.org/flight/788"
    },
    {
        "index": "773",
        "date": "21/08/2014",
        "name": "Eric Bader",
        "location": "Mt. Zion - Golden - US",
        "duration": "0:51",
        "distance": "10.2\u00a0km",
        "xckm": "13.0\u00a0km",
        "xcscore": "19.55",
        "wing": "Ozone Ozone Buzz Z4",
        "links": "http://xc.rmhpa.org/flight/877"
    },
    {
        "index": "774",
        "date": "27/06/2015",
        "name": "Chris Ratay",
        "location": "Mt. Zion - Golden - US",
        "duration": "0:42",
        "distance": "11.5\u00a0km",
        "xckm": "13.0\u00a0km",
        "xcscore": "19.45",
        "wing": "Ozone Rush 4",
        "links": "http://xc.rmhpa.org/flight/1070"
    },
    {
        "index": "775",
        "date": "09/09/2012",
        "name": "Ed Williams",
        "location": "Upper Launch-Foothil... - US",
        "duration": "0:54",
        "distance": "10.0\u00a0km",
        "xckm": "12.9\u00a0km",
        "xcscore": "19.36",
        "wing": "Niviuk Peak 2",
        "links": "http://xc.rmhpa.org/flight/371"
    },
    {
        "index": "776",
        "date": "22/07/2017",
        "name": "Ryan Strong",
        "location": "Edna - US\u00a0[~0.5]",
        "duration": "1:43",
        "distance": "9.6\u00a0km",
        "xckm": "12.8\u00a0km",
        "xcscore": "19.23",
        "wing": "Ozone rush 4",
        "links": "http://xc.rmhpa.org/flight/1562"
    },
    {
        "index": "777",
        "date": "23/06/2014",
        "name": "Jan Voegeli",
        "location": "Mt. Zion - Golden - US",
        "duration": "1:00",
        "distance": "2.3\u00a0km",
        "xckm": "9.5\u00a0km",
        "xcscore": "19.01",
        "wing": "Ozone Mantra R12",
        "links": "http://xc.rmhpa.org/flight/820"
    },
    {
        "index": "778",
        "date": "26/06/2013",
        "name": "Amanda Brodbeck",
        "location": "Wolcott - US",
        "duration": "1:09",
        "distance": "4.3\u00a0km",
        "xckm": "12.6\u00a0km",
        "xcscore": "18.97",
        "wing": "Gradient Nevada",
        "links": "http://xc.rmhpa.org/flight/566"
    },
    {
        "index": "779",
        "date": "19/06/2012",
        "name": "Ed Williams",
        "location": "Mt. Zion - Golden - US",
        "duration": "1:30",
        "distance": "4.8\u00a0km",
        "xckm": "12.6\u00a0km",
        "xcscore": "18.86",
        "wing": "Niviuk Peak 2",
        "links": "http://xc.rmhpa.org/flight/233"
    },
    {
        "index": "780",
        "date": "12/09/2015",
        "name": "Rick Damiani",
        "location": "Mt. Zion - Golden - US",
        "duration": "1:15",
        "distance": "4.1\u00a0km",
        "xckm": "10.8\u00a0km",
        "xcscore": "18.82",
        "wing": "Ozone delta 2",
        "links": "http://xc.rmhpa.org/flight/1129"
    },
    {
        "index": "781",
        "date": "14/03/2015",
        "name": "Jacob Hildebrand",
        "location": "Upper Launch-Foothil... - US",
        "duration": "0:34",
        "distance": "10.0\u00a0km",
        "xckm": "12.5\u00a0km",
        "xcscore": "18.76",
        "wing": "Advance Sigma 9",
        "links": "http://xc.rmhpa.org/flight/940"
    },
    {
        "index": "782",
        "date": "21/10/2012",
        "name": "Jason Ely",
        "location": "Mt. Zion - Golden - US",
        "duration": "1:01",
        "distance": "3.4\u00a0km",
        "xckm": "10.7\u00a0km",
        "xcscore": "18.75",
        "wing": "Ozone Delta",
        "links": "http://xc.rmhpa.org/flight/432"
    },
    {
        "index": "783",
        "date": "11/03/2016",
        "name": "Mike Benzie",
        "location": "Mt. Zion - Golden - US",
        "duration": "1:28",
        "distance": "4.2\u00a0km",
        "xckm": "10.7\u00a0km",
        "xcscore": "18.69",
        "wing": "Gradient Nevada",
        "links": "http://xc.rmhpa.org/flight/1186"
    },
    {
        "index": "784",
        "date": "27/06/2015",
        "name": "Scott Sibs",
        "location": "Mt. Zion - Golden - US",
        "duration": "1:16",
        "distance": "4.5\u00a0km",
        "xckm": "10.6\u00a0km",
        "xcscore": "18.62",
        "wing": "Skywalk Mescal 4M",
        "links": "http://xc.rmhpa.org/flight/1063"
    },
    {
        "index": "785",
        "date": "16/08/2015",
        "name": "William Stites",
        "location": "Upper Launch-Foothil... - US\u00a0[~0.5]",
        "duration": "0:37",
        "distance": "4.6\u00a0km",
        "xckm": "10.6\u00a0km",
        "xcscore": "18.60",
        "wing": "Ozone Delta 2",
        "links": "http://xc.rmhpa.org/flight/1087"
    },
    {
        "index": "786",
        "date": "29/07/2018",
        "name": "Michael Jobin",
        "location": "Mt. Zion - Golden - US",
        "duration": "0:54",
        "distance": "11.0\u00a0km",
        "xckm": "12.4\u00a0km",
        "xcscore": "18.57",
        "wing": "Skywalk poison x alps",
        "links": "http://xc.rmhpa.org/flight/1802"
    },
    {
        "index": "787",
        "date": "21/07/2012",
        "name": "Michael Jobin",
        "location": "Mt. Zion - Golden - US",
        "duration": "1:13",
        "distance": "5.1\u00a0km",
        "xckm": "10.6\u00a0km",
        "xcscore": "18.54",
        "wing": "Aircross Usport Fr",
        "links": "http://xc.rmhpa.org/flight/271"
    },
    {
        "index": "788",
        "date": "15/06/2013",
        "name": "Rick Damiani",
        "location": "Mt. Zion - Golden - US",
        "duration": "1:25",
        "distance": "3.0\u00a0km",
        "xckm": "12.3\u00a0km",
        "xcscore": "18.38",
        "wing": "Gradient A4",
        "links": "http://xc.rmhpa.org/flight/556"
    },
    {
        "index": "789",
        "date": "26/04/2013",
        "name": "Gary Waterman",
        "location": "Mt. Zion - Golden - US",
        "duration": "0:56",
        "distance": "3.2\u00a0km",
        "xckm": "12.2\u00a0km",
        "xcscore": "18.38",
        "wing": "Aircross UCross",
        "links": "http://xc.rmhpa.org/flight/481"
    },
    {
        "index": "790",
        "date": "27/08/2017",
        "name": "Lex Shepherd",
        "location": "Boulder - US",
        "duration": "1:44",
        "distance": "3.8\u00a0km",
        "xckm": "10.5\u00a0km",
        "xcscore": "18.32",
        "wing": "Ozone Alpina2",
        "links": "http://xc.rmhpa.org/flight/1584"
    },
    {
        "index": "791",
        "date": "29/07/2012",
        "name": "Michael Jobin",
        "location": "Mt. Zion - Golden - US",
        "duration": "1:30",
        "distance": "5.4\u00a0km",
        "xckm": "12.2\u00a0km",
        "xcscore": "18.30",
        "wing": "Aircross usport Fr",
        "links": "http://xc.rmhpa.org/flight/293"
    },
    {
        "index": "792",
        "date": "09/06/2013",
        "name": "Amanda Brodbeck",
        "location": "Wolcott - US",
        "duration": "1:21",
        "distance": "3.7\u00a0km",
        "xckm": "9.1\u00a0km",
        "xcscore": "18.27",
        "wing": "Gradient Nevada",
        "links": "http://xc.rmhpa.org/flight/538"
    },
    {
        "index": "793",
        "date": "21/06/2013",
        "name": "Mike Benzie",
        "location": "Woodrat, Oregon - US",
        "duration": "1:34",
        "distance": "5.1\u00a0km",
        "xckm": "12.2\u00a0km",
        "xcscore": "18.24",
        "wing": "Gradient Nevada",
        "links": "http://xc.rmhpa.org/flight/709"
    },
    {
        "index": "794",
        "date": "01/07/2012",
        "name": "Gary Waterman",
        "location": "Villa Grove - US",
        "duration": "1:12",
        "distance": "7.1\u00a0km",
        "xckm": "12.1\u00a0km",
        "xcscore": "18.17",
        "wing": "Aircross UCross",
        "links": "http://xc.rmhpa.org/flight/251"
    },
    {
        "index": "795",
        "date": "23/04/2012",
        "name": "Jason Ely",
        "location": "Mt. Zion - Golden - US",
        "duration": "0:49",
        "distance": "4.1\u00a0km",
        "xckm": "10.3\u00a0km",
        "xcscore": "17.98",
        "wing": "Ozone Rush 3 ",
        "links": "http://xc.rmhpa.org/flight/154"
    },
    {
        "index": "796",
        "date": "01/06/2012",
        "name": "Mike Benzie",
        "location": "Mt. Zion - Golden - US",
        "duration": "1:09",
        "distance": "3.9\u00a0km",
        "xckm": "11.9\u00a0km",
        "xcscore": "17.91",
        "wing": "Gradient Golden 3",
        "links": "http://xc.rmhpa.org/flight/205"
    },
    {
        "index": "797",
        "date": "19/06/2016",
        "name": "Ed Williams",
        "location": "Mt. Zion - Golden - US",
        "duration": "1:11",
        "distance": "6.3\u00a0km",
        "xckm": "11.9\u00a0km",
        "xcscore": "17.90",
        "wing": "Ozone Delta 2",
        "links": "http://xc.rmhpa.org/flight/1245"
    },
    {
        "index": "798",
        "date": "14/05/2017",
        "name": "Shad Preston",
        "location": "Boulder - US",
        "duration": "0:26",
        "distance": "11.0\u00a0km",
        "xckm": "11.9\u00a0km",
        "xcscore": "17.79",
        "wing": "Ozone Mantra M6",
        "links": "http://xc.rmhpa.org/flight/1515"
    },
    {
        "index": "799",
        "date": "12/05/2016",
        "name": "Jacob Hildebrand",
        "location": "Mt. Zion - Golden - US",
        "duration": "0:47",
        "distance": "4.3\u00a0km",
        "xckm": "10.1\u00a0km",
        "xcscore": "17.75",
        "wing": "Advance Sigma 9",
        "links": "http://xc.rmhpa.org/flight/1216"
    },
    {
        "index": "800",
        "date": "19/06/2012",
        "name": "Jason Ely",
        "location": "Mt. Zion - Golden - US",
        "duration": "1:32",
        "distance": "4.6\u00a0km",
        "xckm": "10.1\u00a0km",
        "xcscore": "17.73",
        "wing": "Ozone Delta",
        "links": "http://xc.rmhpa.org/flight/226"
    }
]